{
  "project_id": "proj_0a4580d6-ce2b-4c43-b661-f40f2b5d84a0",
  "run_id": "run_2224dbfb-2424-48db-b26f-5eec2e249011",
  "generated_at": "2026-03-07T20:42:38.660Z",
  "total_duration_ms": 258746,
  "total_cost": 0.024,
  "overall_score": 98.42,
  "overall_grade": "A",
  "passed": true,
  "phases": [
    {
      "agent": "agent1_setting",
      "phase_name": "Setting Refinement",
      "score": {
        "agent": "agent1-setting-refinement",
        "validation_score": 100,
        "quality_score": 100,
        "completeness_score": 100,
        "consistency_score": 100,
        "total": 100,
        "grade": "A",
        "passed": true,
        "tests": [
          {
            "name": "Locations array exists",
            "category": "validation",
            "passed": true,
            "score": 100,
            "weight": 0.5
          },
          {
            "name": "Location validity",
            "category": "validation",
            "passed": true,
            "score": 100,
            "weight": 2,
            "message": "100% valid"
          },
          {
            "name": "Physical plausibility",
            "category": "quality",
            "passed": true,
            "score": 100,
            "weight": 1.5,
            "message": "5/5 plausible"
          },
          {
            "name": "Layout detail",
            "category": "quality",
            "passed": true,
            "score": 100,
            "weight": 1,
            "message": "97% average"
          },
          {
            "name": "Clue justification quality",
            "category": "quality",
            "passed": true,
            "score": 100,
            "weight": 0.5,
            "message": "6/6 well justified"
          },
          {
            "name": "Minimum locations",
            "category": "completeness",
            "passed": true,
            "score": 100,
            "weight": 1.5,
            "message": "5 locations"
          },
          {
            "name": "Physical constraints",
            "category": "completeness",
            "passed": true,
            "score": 100,
            "weight": 0.75
          },
          {
            "name": "Accessibility notes",
            "category": "completeness",
            "passed": true,
            "score": 100,
            "weight": 0.75
          },
          {
            "name": "No duplicate locations",
            "category": "consistency",
            "passed": true,
            "score": 100,
            "weight": 0.5
          }
        ]
      },
      "duration_ms": 7239,
      "cost": 0.0005294817,
      "threshold": 75,
      "passed": true,
      "tests": [
        {
          "name": "Locations array exists",
          "category": "validation",
          "passed": true,
          "score": 100,
          "weight": 0.5
        },
        {
          "name": "Location validity",
          "category": "validation",
          "passed": true,
          "score": 100,
          "weight": 2,
          "message": "100% valid"
        },
        {
          "name": "Physical plausibility",
          "category": "quality",
          "passed": true,
          "score": 100,
          "weight": 1.5,
          "message": "5/5 plausible"
        },
        {
          "name": "Layout detail",
          "category": "quality",
          "passed": true,
          "score": 100,
          "weight": 1,
          "message": "97% average"
        },
        {
          "name": "Clue justification quality",
          "category": "quality",
          "passed": true,
          "score": 100,
          "weight": 0.5,
          "message": "6/6 well justified"
        },
        {
          "name": "Minimum locations",
          "category": "completeness",
          "passed": true,
          "score": 100,
          "weight": 1.5,
          "message": "5 locations"
        },
        {
          "name": "Physical constraints",
          "category": "completeness",
          "passed": true,
          "score": 100,
          "weight": 0.75
        },
        {
          "name": "Accessibility notes",
          "category": "completeness",
          "passed": true,
          "score": 100,
          "weight": 0.75
        },
        {
          "name": "No duplicate locations",
          "category": "consistency",
          "passed": true,
          "score": 100,
          "weight": 0.5
        }
      ]
    },
    {
      "agent": "agent2_cast",
      "phase_name": "Cast Design",
      "score": {
        "agent": "agent2-cast",
        "validation_score": 100.00000000000004,
        "quality_score": 100,
        "completeness_score": 100,
        "consistency_score": 100,
        "total": 100,
        "grade": "A",
        "passed": true,
        "tests": [
          {
            "name": "Cast array exists",
            "category": "validation",
            "passed": true,
            "score": 100,
            "weight": 1
          },
          {
            "name": "Cast not empty",
            "category": "validation",
            "passed": true,
            "score": 100,
            "weight": 1
          },
          {
            "name": "Antoinette Vaux: name",
            "category": "validation",
            "passed": true,
            "score": 100,
            "weight": 0.1
          },
          {
            "name": "Antoinette Vaux: role_archetype",
            "category": "validation",
            "passed": true,
            "score": 100,
            "weight": 0.1
          },
          {
            "name": "Antoinette Vaux: public_persona",
            "category": "validation",
            "passed": true,
            "score": 100,
            "weight": 0.1
          },
          {
            "name": "Antoinette Vaux: private_secret",
            "category": "validation",
            "passed": true,
            "score": 100,
            "weight": 0.1
          },
          {
            "name": "Antoinette Vaux: motive_seed",
            "category": "validation",
            "passed": true,
            "score": 100,
            "weight": 0.1
          },
          {
            "name": "Antoinette Vaux: motive_strength",
            "category": "validation",
            "passed": true,
            "score": 100,
            "weight": 0.1
          },
          {
            "name": "Antoinette Vaux: culprit_eligibility",
            "category": "validation",
            "passed": true,
            "score": 100,
            "weight": 0.1
          },
          {
            "name": "Gordon Brabazon: name",
            "category": "validation",
            "passed": true,
            "score": 100,
            "weight": 0.1
          },
          {
            "name": "Gordon Brabazon: role_archetype",
            "category": "validation",
            "passed": true,
            "score": 100,
            "weight": 0.1
          },
          {
            "name": "Gordon Brabazon: public_persona",
            "category": "validation",
            "passed": true,
            "score": 100,
            "weight": 0.1
          },
          {
            "name": "Gordon Brabazon: private_secret",
            "category": "validation",
            "passed": true,
            "score": 100,
            "weight": 0.1
          },
          {
            "name": "Gordon Brabazon: motive_seed",
            "category": "validation",
            "passed": true,
            "score": 100,
            "weight": 0.1
          },
          {
            "name": "Gordon Brabazon: motive_strength",
            "category": "validation",
            "passed": true,
            "score": 100,
            "weight": 0.1
          },
          {
            "name": "Gordon Brabazon: culprit_eligibility",
            "category": "validation",
            "passed": true,
            "score": 100,
            "weight": 0.1
          },
          {
            "name": "Paul Courtenay: name",
            "category": "validation",
            "passed": true,
            "score": 100,
            "weight": 0.1
          },
          {
            "name": "Paul Courtenay: role_archetype",
            "category": "validation",
            "passed": true,
            "score": 100,
            "weight": 0.1
          },
          {
            "name": "Paul Courtenay: public_persona",
            "category": "validation",
            "passed": true,
            "score": 100,
            "weight": 0.1
          },
          {
            "name": "Paul Courtenay: private_secret",
            "category": "validation",
            "passed": true,
            "score": 100,
            "weight": 0.1
          },
          {
            "name": "Paul Courtenay: motive_seed",
            "category": "validation",
            "passed": true,
            "score": 100,
            "weight": 0.1
          },
          {
            "name": "Paul Courtenay: motive_strength",
            "category": "validation",
            "passed": true,
            "score": 100,
            "weight": 0.1
          },
          {
            "name": "Paul Courtenay: culprit_eligibility",
            "category": "validation",
            "passed": true,
            "score": 100,
            "weight": 0.1
          },
          {
            "name": "Claire Latour: name",
            "category": "validation",
            "passed": true,
            "score": 100,
            "weight": 0.1
          },
          {
            "name": "Claire Latour: role_archetype",
            "category": "validation",
            "passed": true,
            "score": 100,
            "weight": 0.1
          },
          {
            "name": "Claire Latour: public_persona",
            "category": "validation",
            "passed": true,
            "score": 100,
            "weight": 0.1
          },
          {
            "name": "Claire Latour: private_secret",
            "category": "validation",
            "passed": true,
            "score": 100,
            "weight": 0.1
          },
          {
            "name": "Claire Latour: motive_seed",
            "category": "validation",
            "passed": true,
            "score": 100,
            "weight": 0.1
          },
          {
            "name": "Claire Latour: motive_strength",
            "category": "validation",
            "passed": true,
            "score": 100,
            "weight": 0.1
          },
          {
            "name": "Claire Latour: culprit_eligibility",
            "category": "validation",
            "passed": true,
            "score": 100,
            "weight": 0.1
          },
          {
            "name": "Alan Devereux: name",
            "category": "validation",
            "passed": true,
            "score": 100,
            "weight": 0.1
          },
          {
            "name": "Alan Devereux: role_archetype",
            "category": "validation",
            "passed": true,
            "score": 100,
            "weight": 0.1
          },
          {
            "name": "Alan Devereux: public_persona",
            "category": "validation",
            "passed": true,
            "score": 100,
            "weight": 0.1
          },
          {
            "name": "Alan Devereux: private_secret",
            "category": "validation",
            "passed": true,
            "score": 100,
            "weight": 0.1
          },
          {
            "name": "Alan Devereux: motive_seed",
            "category": "validation",
            "passed": true,
            "score": 100,
            "weight": 0.1
          },
          {
            "name": "Alan Devereux: motive_strength",
            "category": "validation",
            "passed": true,
            "score": 100,
            "weight": 0.1
          },
          {
            "name": "Alan Devereux: culprit_eligibility",
            "category": "validation",
            "passed": true,
            "score": 100,
            "weight": 0.1
          },
          {
            "name": "Character validity rate",
            "category": "validation",
            "passed": true,
            "score": 100,
            "weight": 2,
            "message": "All characters valid"
          },
          {
            "name": "No duplicate names",
            "category": "validation",
            "passed": true,
            "score": 100,
            "weight": 1,
            "message": "No duplicates found"
          },
          {
            "name": "Character depth",
            "category": "quality",
            "passed": true,
            "score": 100,
            "weight": 2,
            "message": "Average depth: 84%"
          },
          {
            "name": "Motive strength variety",
            "category": "quality",
            "passed": true,
            "score": 100,
            "weight": 1,
            "message": "Multiple motive strengths present"
          },
          {
            "name": "Relationship density",
            "category": "quality",
            "passed": true,
            "score": 100,
            "weight": 1,
            "message": "Avg 2.0 per character"
          },
          {
            "name": "Relationships reference cast",
            "category": "quality",
            "passed": true,
            "score": 100,
            "weight": 1
          },
          {
            "name": "Cast size appropriate",
            "category": "completeness",
            "passed": true,
            "score": 100,
            "weight": 1,
            "message": "Complete (5 items)"
          },
          {
            "name": "Sufficient suspects",
            "category": "completeness",
            "passed": true,
            "score": 100,
            "weight": 2,
            "message": "3 eligible suspects"
          },
          {
            "name": "Role diversity",
            "category": "completeness",
            "passed": true,
            "score": 100,
            "weight": 1,
            "message": "4 unique archetypes"
          },
          {
            "name": "Has eligible suspects",
            "category": "consistency",
            "passed": true,
            "score": 100,
            "weight": 1
          },
          {
            "name": "Relationship reciprocity",
            "category": "consistency",
            "passed": true,
            "score": 100,
            "weight": 1,
            "message": "100% reciprocal"
          }
        ]
      },
      "duration_ms": 11725,
      "cost": 0,
      "threshold": 75,
      "passed": true,
      "tests": [
        {
          "name": "Cast array exists",
          "category": "validation",
          "passed": true,
          "score": 100,
          "weight": 1
        },
        {
          "name": "Cast not empty",
          "category": "validation",
          "passed": true,
          "score": 100,
          "weight": 1
        },
        {
          "name": "Antoinette Vaux: name",
          "category": "validation",
          "passed": true,
          "score": 100,
          "weight": 0.1
        },
        {
          "name": "Antoinette Vaux: role_archetype",
          "category": "validation",
          "passed": true,
          "score": 100,
          "weight": 0.1
        },
        {
          "name": "Antoinette Vaux: public_persona",
          "category": "validation",
          "passed": true,
          "score": 100,
          "weight": 0.1
        },
        {
          "name": "Antoinette Vaux: private_secret",
          "category": "validation",
          "passed": true,
          "score": 100,
          "weight": 0.1
        },
        {
          "name": "Antoinette Vaux: motive_seed",
          "category": "validation",
          "passed": true,
          "score": 100,
          "weight": 0.1
        },
        {
          "name": "Antoinette Vaux: motive_strength",
          "category": "validation",
          "passed": true,
          "score": 100,
          "weight": 0.1
        },
        {
          "name": "Antoinette Vaux: culprit_eligibility",
          "category": "validation",
          "passed": true,
          "score": 100,
          "weight": 0.1
        },
        {
          "name": "Gordon Brabazon: name",
          "category": "validation",
          "passed": true,
          "score": 100,
          "weight": 0.1
        },
        {
          "name": "Gordon Brabazon: role_archetype",
          "category": "validation",
          "passed": true,
          "score": 100,
          "weight": 0.1
        },
        {
          "name": "Gordon Brabazon: public_persona",
          "category": "validation",
          "passed": true,
          "score": 100,
          "weight": 0.1
        },
        {
          "name": "Gordon Brabazon: private_secret",
          "category": "validation",
          "passed": true,
          "score": 100,
          "weight": 0.1
        },
        {
          "name": "Gordon Brabazon: motive_seed",
          "category": "validation",
          "passed": true,
          "score": 100,
          "weight": 0.1
        },
        {
          "name": "Gordon Brabazon: motive_strength",
          "category": "validation",
          "passed": true,
          "score": 100,
          "weight": 0.1
        },
        {
          "name": "Gordon Brabazon: culprit_eligibility",
          "category": "validation",
          "passed": true,
          "score": 100,
          "weight": 0.1
        },
        {
          "name": "Paul Courtenay: name",
          "category": "validation",
          "passed": true,
          "score": 100,
          "weight": 0.1
        },
        {
          "name": "Paul Courtenay: role_archetype",
          "category": "validation",
          "passed": true,
          "score": 100,
          "weight": 0.1
        },
        {
          "name": "Paul Courtenay: public_persona",
          "category": "validation",
          "passed": true,
          "score": 100,
          "weight": 0.1
        },
        {
          "name": "Paul Courtenay: private_secret",
          "category": "validation",
          "passed": true,
          "score": 100,
          "weight": 0.1
        },
        {
          "name": "Paul Courtenay: motive_seed",
          "category": "validation",
          "passed": true,
          "score": 100,
          "weight": 0.1
        },
        {
          "name": "Paul Courtenay: motive_strength",
          "category": "validation",
          "passed": true,
          "score": 100,
          "weight": 0.1
        },
        {
          "name": "Paul Courtenay: culprit_eligibility",
          "category": "validation",
          "passed": true,
          "score": 100,
          "weight": 0.1
        },
        {
          "name": "Claire Latour: name",
          "category": "validation",
          "passed": true,
          "score": 100,
          "weight": 0.1
        },
        {
          "name": "Claire Latour: role_archetype",
          "category": "validation",
          "passed": true,
          "score": 100,
          "weight": 0.1
        },
        {
          "name": "Claire Latour: public_persona",
          "category": "validation",
          "passed": true,
          "score": 100,
          "weight": 0.1
        },
        {
          "name": "Claire Latour: private_secret",
          "category": "validation",
          "passed": true,
          "score": 100,
          "weight": 0.1
        },
        {
          "name": "Claire Latour: motive_seed",
          "category": "validation",
          "passed": true,
          "score": 100,
          "weight": 0.1
        },
        {
          "name": "Claire Latour: motive_strength",
          "category": "validation",
          "passed": true,
          "score": 100,
          "weight": 0.1
        },
        {
          "name": "Claire Latour: culprit_eligibility",
          "category": "validation",
          "passed": true,
          "score": 100,
          "weight": 0.1
        },
        {
          "name": "Alan Devereux: name",
          "category": "validation",
          "passed": true,
          "score": 100,
          "weight": 0.1
        },
        {
          "name": "Alan Devereux: role_archetype",
          "category": "validation",
          "passed": true,
          "score": 100,
          "weight": 0.1
        },
        {
          "name": "Alan Devereux: public_persona",
          "category": "validation",
          "passed": true,
          "score": 100,
          "weight": 0.1
        },
        {
          "name": "Alan Devereux: private_secret",
          "category": "validation",
          "passed": true,
          "score": 100,
          "weight": 0.1
        },
        {
          "name": "Alan Devereux: motive_seed",
          "category": "validation",
          "passed": true,
          "score": 100,
          "weight": 0.1
        },
        {
          "name": "Alan Devereux: motive_strength",
          "category": "validation",
          "passed": true,
          "score": 100,
          "weight": 0.1
        },
        {
          "name": "Alan Devereux: culprit_eligibility",
          "category": "validation",
          "passed": true,
          "score": 100,
          "weight": 0.1
        },
        {
          "name": "Character validity rate",
          "category": "validation",
          "passed": true,
          "score": 100,
          "weight": 2,
          "message": "All characters valid"
        },
        {
          "name": "No duplicate names",
          "category": "validation",
          "passed": true,
          "score": 100,
          "weight": 1,
          "message": "No duplicates found"
        },
        {
          "name": "Character depth",
          "category": "quality",
          "passed": true,
          "score": 100,
          "weight": 2,
          "message": "Average depth: 84%"
        },
        {
          "name": "Motive strength variety",
          "category": "quality",
          "passed": true,
          "score": 100,
          "weight": 1,
          "message": "Multiple motive strengths present"
        },
        {
          "name": "Relationship density",
          "category": "quality",
          "passed": true,
          "score": 100,
          "weight": 1,
          "message": "Avg 2.0 per character"
        },
        {
          "name": "Relationships reference cast",
          "category": "quality",
          "passed": true,
          "score": 100,
          "weight": 1
        },
        {
          "name": "Cast size appropriate",
          "category": "completeness",
          "passed": true,
          "score": 100,
          "weight": 1,
          "message": "Complete (5 items)"
        },
        {
          "name": "Sufficient suspects",
          "category": "completeness",
          "passed": true,
          "score": 100,
          "weight": 2,
          "message": "3 eligible suspects"
        },
        {
          "name": "Role diversity",
          "category": "completeness",
          "passed": true,
          "score": 100,
          "weight": 1,
          "message": "4 unique archetypes"
        },
        {
          "name": "Has eligible suspects",
          "category": "consistency",
          "passed": true,
          "score": 100,
          "weight": 1
        },
        {
          "name": "Relationship reciprocity",
          "category": "consistency",
          "passed": true,
          "score": 100,
          "weight": 1,
          "message": "100% reciprocal"
        }
      ]
    },
    {
      "agent": "agent2e_background_context",
      "phase_name": "Background Context",
      "score": {
        "agent": "agent2e-background",
        "validation_score": 100,
        "quality_score": 100,
        "completeness_score": 90,
        "consistency_score": 100,
        "total": 98,
        "grade": "A",
        "passed": true,
        "tests": [
          {
            "name": "Era decade present",
            "category": "validation",
            "passed": true,
            "score": 100,
            "weight": 1
          },
          {
            "name": "Tech capabilities present",
            "category": "validation",
            "passed": true,
            "score": 100,
            "weight": 1
          },
          {
            "name": "Forensic capabilities present",
            "category": "validation",
            "passed": true,
            "score": 100,
            "weight": 1
          },
          {
            "name": "Location type present",
            "category": "validation",
            "passed": true,
            "score": 100,
            "weight": 1
          },
          {
            "name": "Physical constraints present",
            "category": "validation",
            "passed": true,
            "score": 100,
            "weight": 1
          },
          {
            "name": "Constraints section present",
            "category": "validation",
            "passed": true,
            "score": 100,
            "weight": 0.5
          },
          {
            "name": "Tech capabilities detailed",
            "category": "quality",
            "passed": true,
            "score": 100,
            "weight": 1,
            "message": "4 items"
          },
          {
            "name": "Forensic capabilities detailed",
            "category": "quality",
            "passed": true,
            "score": 100,
            "weight": 1,
            "message": "3 items"
          },
          {
            "name": "Communications detailed",
            "category": "quality",
            "passed": true,
            "score": 100,
            "weight": 1,
            "message": "3 items"
          },
          {
            "name": "Transportation detailed",
            "category": "quality",
            "passed": true,
            "score": 100,
            "weight": 1,
            "message": "3 items"
          },
          {
            "name": "Social norms detailed",
            "category": "quality",
            "passed": true,
            "score": 100,
            "weight": 1,
            "message": "4 items"
          },
          {
            "name": "Physical constraints detailed",
            "category": "quality",
            "passed": true,
            "score": 100,
            "weight": 1,
            "message": "4 items"
          },
          {
            "name": "Security features detailed",
            "category": "quality",
            "passed": true,
            "score": 100,
            "weight": 1,
            "message": "3 items"
          },
          {
            "name": "Accessibility detailed",
            "category": "quality",
            "passed": true,
            "score": 100,
            "weight": 1,
            "message": "3 items"
          },
          {
            "name": "Atmosphere detailed",
            "category": "quality",
            "passed": true,
            "score": 100,
            "weight": 1,
            "message": "3 items"
          },
          {
            "name": "Era background complete",
            "category": "completeness",
            "passed": true,
            "score": 100,
            "weight": 2,
            "message": "Era completeness: 100%"
          },
          {
            "name": "Location background complete",
            "category": "completeness",
            "passed": true,
            "score": 100,
            "weight": 2,
            "message": "Location completeness: 100%"
          },
          {
            "name": "Constraints defined",
            "category": "completeness",
            "passed": true,
            "score": 50,
            "weight": 1,
            "message": "Constraints completeness: 50%"
          },
          {
            "name": "Era/Location compatibility",
            "category": "consistency",
            "passed": true,
            "score": 100,
            "weight": 1,
            "message": "Era and location background both present"
          },
          {
            "name": "Constraint/Capability consistency",
            "category": "consistency",
            "passed": true,
            "score": 100,
            "weight": 1,
            "message": "No anachronism conflicts detected"
          }
        ]
      },
      "duration_ms": 1808,
      "cost": 0.00017870985,
      "threshold": 70,
      "passed": true,
      "tests": [
        {
          "name": "Era decade present",
          "category": "validation",
          "passed": true,
          "score": 100,
          "weight": 1
        },
        {
          "name": "Tech capabilities present",
          "category": "validation",
          "passed": true,
          "score": 100,
          "weight": 1
        },
        {
          "name": "Forensic capabilities present",
          "category": "validation",
          "passed": true,
          "score": 100,
          "weight": 1
        },
        {
          "name": "Location type present",
          "category": "validation",
          "passed": true,
          "score": 100,
          "weight": 1
        },
        {
          "name": "Physical constraints present",
          "category": "validation",
          "passed": true,
          "score": 100,
          "weight": 1
        },
        {
          "name": "Constraints section present",
          "category": "validation",
          "passed": true,
          "score": 100,
          "weight": 0.5
        },
        {
          "name": "Tech capabilities detailed",
          "category": "quality",
          "passed": true,
          "score": 100,
          "weight": 1,
          "message": "4 items"
        },
        {
          "name": "Forensic capabilities detailed",
          "category": "quality",
          "passed": true,
          "score": 100,
          "weight": 1,
          "message": "3 items"
        },
        {
          "name": "Communications detailed",
          "category": "quality",
          "passed": true,
          "score": 100,
          "weight": 1,
          "message": "3 items"
        },
        {
          "name": "Transportation detailed",
          "category": "quality",
          "passed": true,
          "score": 100,
          "weight": 1,
          "message": "3 items"
        },
        {
          "name": "Social norms detailed",
          "category": "quality",
          "passed": true,
          "score": 100,
          "weight": 1,
          "message": "4 items"
        },
        {
          "name": "Physical constraints detailed",
          "category": "quality",
          "passed": true,
          "score": 100,
          "weight": 1,
          "message": "4 items"
        },
        {
          "name": "Security features detailed",
          "category": "quality",
          "passed": true,
          "score": 100,
          "weight": 1,
          "message": "3 items"
        },
        {
          "name": "Accessibility detailed",
          "category": "quality",
          "passed": true,
          "score": 100,
          "weight": 1,
          "message": "3 items"
        },
        {
          "name": "Atmosphere detailed",
          "category": "quality",
          "passed": true,
          "score": 100,
          "weight": 1,
          "message": "3 items"
        },
        {
          "name": "Era background complete",
          "category": "completeness",
          "passed": true,
          "score": 100,
          "weight": 2,
          "message": "Era completeness: 100%"
        },
        {
          "name": "Location background complete",
          "category": "completeness",
          "passed": true,
          "score": 100,
          "weight": 2,
          "message": "Location completeness: 100%"
        },
        {
          "name": "Constraints defined",
          "category": "completeness",
          "passed": true,
          "score": 50,
          "weight": 1,
          "message": "Constraints completeness: 50%"
        },
        {
          "name": "Era/Location compatibility",
          "category": "consistency",
          "passed": true,
          "score": 100,
          "weight": 1,
          "message": "Era and location background both present"
        },
        {
          "name": "Constraint/Capability consistency",
          "category": "consistency",
          "passed": true,
          "score": 100,
          "weight": 1,
          "message": "No anachronism conflicts detected"
        }
      ]
    },
    {
      "agent": "agent3b_hard_logic_devices",
      "phase_name": "Hard Logic Devices",
      "score": {
        "agent": "agent4-hard-logic",
        "validation_score": 99.99999999999996,
        "quality_score": 100,
        "completeness_score": 100,
        "consistency_score": 100,
        "total": 100,
        "grade": "A",
        "passed": true,
        "tests": [
          {
            "name": "Devices array exists",
            "category": "validation",
            "passed": true,
            "score": 100,
            "weight": 1
          },
          {
            "name": "device_1: has ID",
            "category": "validation",
            "passed": true,
            "score": 100,
            "weight": 0.1
          },
          {
            "name": "device_1: has type",
            "category": "validation",
            "passed": true,
            "score": 100,
            "weight": 0.1
          },
          {
            "name": "device_1: has justification",
            "category": "validation",
            "passed": true,
            "score": 100,
            "weight": 0.1
          },
          {
            "name": "device_2: has ID",
            "category": "validation",
            "passed": true,
            "score": 100,
            "weight": 0.1
          },
          {
            "name": "device_2: has type",
            "category": "validation",
            "passed": true,
            "score": 100,
            "weight": 0.1
          },
          {
            "name": "device_2: has justification",
            "category": "validation",
            "passed": true,
            "score": 100,
            "weight": 0.1
          },
          {
            "name": "device_3: has ID",
            "category": "validation",
            "passed": true,
            "score": 100,
            "weight": 0.1
          },
          {
            "name": "device_3: has type",
            "category": "validation",
            "passed": true,
            "score": 100,
            "weight": 0.1
          },
          {
            "name": "device_3: has justification",
            "category": "validation",
            "passed": true,
            "score": 100,
            "weight": 0.1
          },
          {
            "name": "device_4: has ID",
            "category": "validation",
            "passed": true,
            "score": 100,
            "weight": 0.1
          },
          {
            "name": "device_4: has type",
            "category": "validation",
            "passed": true,
            "score": 100,
            "weight": 0.1
          },
          {
            "name": "device_4: has justification",
            "category": "validation",
            "passed": true,
            "score": 100,
            "weight": 0.1
          },
          {
            "name": "device_5: has ID",
            "category": "validation",
            "passed": true,
            "score": 100,
            "weight": 0.1
          },
          {
            "name": "device_5: has type",
            "category": "validation",
            "passed": true,
            "score": 100,
            "weight": 0.1
          },
          {
            "name": "device_5: has justification",
            "category": "validation",
            "passed": true,
            "score": 100,
            "weight": 0.1
          },
          {
            "name": "Device validity rate",
            "category": "validation",
            "passed": true,
            "score": 100,
            "weight": 2,
            "message": "100% valid"
          },
          {
            "name": "Device detail quality",
            "category": "quality",
            "passed": true,
            "score": 100,
            "weight": 2,
            "message": "Average depth: 100%"
          },
          {
            "name": "Devices have implications",
            "category": "quality",
            "passed": true,
            "score": 100,
            "weight": 1,
            "message": "5/5 devices"
          },
          {
            "name": "Minimum devices present",
            "category": "completeness",
            "passed": true,
            "score": 100,
            "weight": 2,
            "message": "5 devices"
          },
          {
            "name": "Device type diversity",
            "category": "completeness",
            "passed": true,
            "score": 100,
            "weight": 1,
            "message": "3 unique types"
          },
          {
            "name": "No duplicate device IDs",
            "category": "consistency",
            "passed": true,
            "score": 100,
            "weight": 1
          },
          {
            "name": "Implications are meaningful",
            "category": "consistency",
            "passed": true,
            "score": 100,
            "weight": 1
          }
        ]
      },
      "duration_ms": 10357,
      "cost": 0.00087738585,
      "threshold": 85,
      "passed": true,
      "tests": [
        {
          "name": "Devices array exists",
          "category": "validation",
          "passed": true,
          "score": 100,
          "weight": 1
        },
        {
          "name": "device_1: has ID",
          "category": "validation",
          "passed": true,
          "score": 100,
          "weight": 0.1
        },
        {
          "name": "device_1: has type",
          "category": "validation",
          "passed": true,
          "score": 100,
          "weight": 0.1
        },
        {
          "name": "device_1: has justification",
          "category": "validation",
          "passed": true,
          "score": 100,
          "weight": 0.1
        },
        {
          "name": "device_2: has ID",
          "category": "validation",
          "passed": true,
          "score": 100,
          "weight": 0.1
        },
        {
          "name": "device_2: has type",
          "category": "validation",
          "passed": true,
          "score": 100,
          "weight": 0.1
        },
        {
          "name": "device_2: has justification",
          "category": "validation",
          "passed": true,
          "score": 100,
          "weight": 0.1
        },
        {
          "name": "device_3: has ID",
          "category": "validation",
          "passed": true,
          "score": 100,
          "weight": 0.1
        },
        {
          "name": "device_3: has type",
          "category": "validation",
          "passed": true,
          "score": 100,
          "weight": 0.1
        },
        {
          "name": "device_3: has justification",
          "category": "validation",
          "passed": true,
          "score": 100,
          "weight": 0.1
        },
        {
          "name": "device_4: has ID",
          "category": "validation",
          "passed": true,
          "score": 100,
          "weight": 0.1
        },
        {
          "name": "device_4: has type",
          "category": "validation",
          "passed": true,
          "score": 100,
          "weight": 0.1
        },
        {
          "name": "device_4: has justification",
          "category": "validation",
          "passed": true,
          "score": 100,
          "weight": 0.1
        },
        {
          "name": "device_5: has ID",
          "category": "validation",
          "passed": true,
          "score": 100,
          "weight": 0.1
        },
        {
          "name": "device_5: has type",
          "category": "validation",
          "passed": true,
          "score": 100,
          "weight": 0.1
        },
        {
          "name": "device_5: has justification",
          "category": "validation",
          "passed": true,
          "score": 100,
          "weight": 0.1
        },
        {
          "name": "Device validity rate",
          "category": "validation",
          "passed": true,
          "score": 100,
          "weight": 2,
          "message": "100% valid"
        },
        {
          "name": "Device detail quality",
          "category": "quality",
          "passed": true,
          "score": 100,
          "weight": 2,
          "message": "Average depth: 100%"
        },
        {
          "name": "Devices have implications",
          "category": "quality",
          "passed": true,
          "score": 100,
          "weight": 1,
          "message": "5/5 devices"
        },
        {
          "name": "Minimum devices present",
          "category": "completeness",
          "passed": true,
          "score": 100,
          "weight": 2,
          "message": "5 devices"
        },
        {
          "name": "Device type diversity",
          "category": "completeness",
          "passed": true,
          "score": 100,
          "weight": 1,
          "message": "3 unique types"
        },
        {
          "name": "No duplicate device IDs",
          "category": "consistency",
          "passed": true,
          "score": 100,
          "weight": 1
        },
        {
          "name": "Implications are meaningful",
          "category": "consistency",
          "passed": true,
          "score": 100,
          "weight": 1
        }
      ]
    },
    {
      "agent": "agent3_cml",
      "phase_name": "CML Generation",
      "score": {
        "agent": "agent3-cml-generation",
        "validation_score": 100,
        "quality_score": 100,
        "completeness_score": 100,
        "consistency_score": 100,
        "total": 100,
        "grade": "A",
        "passed": true,
        "tests": [
          {
            "name": "Schema validation",
            "category": "validation",
            "passed": true,
            "score": 100,
            "weight": 2,
            "message": "Valid after 1 attempt(s)"
          },
          {
            "name": "Structural revision (Agent 4)",
            "category": "quality",
            "passed": true,
            "score": 100,
            "weight": 1,
            "message": "No structural revision needed"
          }
        ]
      },
      "duration_ms": 23771,
      "cost": 0.0024127785,
      "threshold": 75,
      "passed": true,
      "tests": [
        {
          "name": "Schema validation",
          "category": "validation",
          "passed": true,
          "score": 100,
          "weight": 2,
          "message": "Valid after 1 attempt(s)"
        },
        {
          "name": "Structural revision (Agent 4)",
          "category": "quality",
          "passed": true,
          "score": 100,
          "weight": 1,
          "message": "No structural revision needed"
        }
      ]
    },
    {
      "agent": "agent8_novelty",
      "phase_name": "Novelty Audit",
      "score": {
        "agent": "agent8-novelty-audit",
        "validation_score": 100,
        "quality_score": 100,
        "completeness_score": 100,
        "consistency_score": 100,
        "total": 100,
        "grade": "A",
        "passed": true,
        "tests": [
          {
            "name": "Novelty check",
            "category": "validation",
            "passed": true,
            "score": 100,
            "weight": 1,
            "message": "Skipped (threshold ≥ 1.0 or skipNoveltyCheck set)"
          }
        ]
      },
      "duration_ms": 0,
      "cost": 0,
      "threshold": 75,
      "passed": true,
      "tests": [
        {
          "name": "Novelty check",
          "category": "validation",
          "passed": true,
          "score": 100,
          "weight": 1,
          "message": "Skipped (threshold ≥ 1.0 or skipNoveltyCheck set)"
        }
      ]
    },
    {
      "agent": "agent5_clues",
      "phase_name": "Clue Distribution",
      "score": {
        "agent": "agent5-clue-distribution",
        "validation_score": 100,
        "quality_score": 100,
        "completeness_score": 100,
        "consistency_score": 100,
        "total": 100,
        "grade": "A",
        "passed": true,
        "tests": [
          {
            "name": "Clue count",
            "category": "completeness",
            "passed": true,
            "score": 100,
            "weight": 1.5,
            "message": "8 clues distributed"
          },
          {
            "name": "Guardrail compliance",
            "category": "validation",
            "passed": true,
            "score": 100,
            "weight": 2,
            "message": "All guardrails passed"
          },
          {
            "name": "Inference coverage",
            "category": "validation",
            "passed": true,
            "score": 100,
            "weight": 2,
            "message": "Full inference coverage (2 minor issues)"
          }
        ]
      },
      "duration_ms": 9480,
      "cost": 0.0007466447999999999,
      "threshold": 75,
      "passed": true,
      "tests": [
        {
          "name": "Clue count",
          "category": "completeness",
          "passed": true,
          "score": 100,
          "weight": 1.5,
          "message": "8 clues distributed"
        },
        {
          "name": "Guardrail compliance",
          "category": "validation",
          "passed": true,
          "score": 100,
          "weight": 2,
          "message": "All guardrails passed"
        },
        {
          "name": "Inference coverage",
          "category": "validation",
          "passed": true,
          "score": 100,
          "weight": 2,
          "message": "Full inference coverage (2 minor issues)"
        }
      ]
    },
    {
      "agent": "agent6_fairplay",
      "phase_name": "Fair-play Audit",
      "score": {
        "agent": "agent6-fair-play-audit",
        "validation_score": 100,
        "quality_score": 100,
        "completeness_score": 100,
        "consistency_score": 100,
        "total": 100,
        "grade": "A",
        "passed": true,
        "tests": [
          {
            "name": "Overall fair play status",
            "category": "validation",
            "passed": true,
            "score": 100,
            "weight": 2,
            "message": "Status: pass"
          }
        ]
      },
      "duration_ms": 5257,
      "cost": 0.0006444503999999999,
      "threshold": 75,
      "passed": true,
      "tests": [
        {
          "name": "Overall fair play status",
          "category": "validation",
          "passed": true,
          "score": 100,
          "weight": 2,
          "message": "Status: pass"
        }
      ]
    },
    {
      "agent": "agent7_narrative",
      "phase_name": "Narrative Outline",
      "score": {
        "agent": "agent7-narrative-outline",
        "validation_score": 91.66666666666667,
        "quality_score": 86.66666666666667,
        "completeness_score": 100,
        "consistency_score": 100,
        "total": 93,
        "grade": "A",
        "passed": true,
        "tests": [
          {
            "name": "Chapters array exists",
            "category": "validation",
            "passed": true,
            "score": 100,
            "weight": 0.5
          },
          {
            "name": "Chapter count",
            "category": "validation",
            "passed": true,
            "score": 75,
            "weight": 2,
            "message": "17 chapters (expected 12)",
            "severity": "major"
          },
          {
            "name": "Chapter structure",
            "category": "validation",
            "passed": true,
            "score": 100,
            "weight": 2,
            "message": "100% valid"
          },
          {
            "name": "Discriminating test scene",
            "category": "validation",
            "passed": true,
            "score": 100,
            "weight": 1.5
          },
          {
            "name": "Scene detail quality",
            "category": "quality",
            "passed": true,
            "score": 100,
            "weight": 1.5,
            "message": "93% average"
          },
          {
            "name": "Clue pacing",
            "category": "quality",
            "passed": true,
            "score": 60,
            "weight": 1,
            "message": "6/17 chapters have clues"
          },
          {
            "name": "Chapter titles",
            "category": "quality",
            "passed": true,
            "score": 100,
            "weight": 0.5,
            "message": "17/17"
          },
          {
            "name": "Discriminating test in outline",
            "category": "completeness",
            "passed": true,
            "score": 100,
            "weight": 1
          },
          {
            "name": "Character name consistency",
            "category": "consistency",
            "passed": true,
            "score": 100,
            "weight": 1.5,
            "message": "100% match cast"
          },
          {
            "name": "No duplicate scene IDs",
            "category": "consistency",
            "passed": true,
            "score": 100,
            "weight": 0.5
          }
        ]
      },
      "duration_ms": 34650,
      "cost": 0.0026919882000000003,
      "threshold": 75,
      "passed": true,
      "tests": [
        {
          "name": "Chapters array exists",
          "category": "validation",
          "passed": true,
          "score": 100,
          "weight": 0.5
        },
        {
          "name": "Chapter count",
          "category": "validation",
          "passed": true,
          "score": 75,
          "weight": 2,
          "message": "17 chapters (expected 12)",
          "severity": "major"
        },
        {
          "name": "Chapter structure",
          "category": "validation",
          "passed": true,
          "score": 100,
          "weight": 2,
          "message": "100% valid"
        },
        {
          "name": "Discriminating test scene",
          "category": "validation",
          "passed": true,
          "score": 100,
          "weight": 1.5
        },
        {
          "name": "Scene detail quality",
          "category": "quality",
          "passed": true,
          "score": 100,
          "weight": 1.5,
          "message": "93% average"
        },
        {
          "name": "Clue pacing",
          "category": "quality",
          "passed": true,
          "score": 60,
          "weight": 1,
          "message": "6/17 chapters have clues"
        },
        {
          "name": "Chapter titles",
          "category": "quality",
          "passed": true,
          "score": 100,
          "weight": 0.5,
          "message": "17/17"
        },
        {
          "name": "Discriminating test in outline",
          "category": "completeness",
          "passed": true,
          "score": 100,
          "weight": 1
        },
        {
          "name": "Character name consistency",
          "category": "consistency",
          "passed": true,
          "score": 100,
          "weight": 1.5,
          "message": "100% match cast"
        },
        {
          "name": "No duplicate scene IDs",
          "category": "consistency",
          "passed": true,
          "score": 100,
          "weight": 0.5
        }
      ]
    },
    {
      "agent": "agent2b_profiles",
      "phase_name": "Character Profiles",
      "score": {
        "agent": "agent2b-character-profiles",
        "validation_score": 99.99999999999997,
        "quality_score": 100,
        "completeness_score": 100,
        "consistency_score": 100,
        "total": 100,
        "grade": "A",
        "passed": true,
        "tests": [
          {
            "name": "Profiles array exists",
            "category": "validation",
            "passed": true,
            "score": 100,
            "weight": 1
          },
          {
            "name": "Antoinette Vaux: character_name",
            "category": "validation",
            "passed": true,
            "score": 100,
            "weight": 0.1
          },
          {
            "name": "Antoinette Vaux: public_persona",
            "category": "validation",
            "passed": true,
            "score": 100,
            "weight": 0.1
          },
          {
            "name": "Antoinette Vaux: private_secrets",
            "category": "validation",
            "passed": true,
            "score": 100,
            "weight": 0.1
          },
          {
            "name": "Antoinette Vaux: stakes",
            "category": "validation",
            "passed": true,
            "score": 100,
            "weight": 0.1
          },
          {
            "name": "Gordon Brabazon: character_name",
            "category": "validation",
            "passed": true,
            "score": 100,
            "weight": 0.1
          },
          {
            "name": "Gordon Brabazon: public_persona",
            "category": "validation",
            "passed": true,
            "score": 100,
            "weight": 0.1
          },
          {
            "name": "Gordon Brabazon: private_secrets",
            "category": "validation",
            "passed": true,
            "score": 100,
            "weight": 0.1
          },
          {
            "name": "Gordon Brabazon: stakes",
            "category": "validation",
            "passed": true,
            "score": 100,
            "weight": 0.1
          },
          {
            "name": "Paul Courtenay: character_name",
            "category": "validation",
            "passed": true,
            "score": 100,
            "weight": 0.1
          },
          {
            "name": "Paul Courtenay: public_persona",
            "category": "validation",
            "passed": true,
            "score": 100,
            "weight": 0.1
          },
          {
            "name": "Paul Courtenay: private_secrets",
            "category": "validation",
            "passed": true,
            "score": 100,
            "weight": 0.1
          },
          {
            "name": "Paul Courtenay: stakes",
            "category": "validation",
            "passed": true,
            "score": 100,
            "weight": 0.1
          },
          {
            "name": "Claire Latour: character_name",
            "category": "validation",
            "passed": true,
            "score": 100,
            "weight": 0.1
          },
          {
            "name": "Claire Latour: public_persona",
            "category": "validation",
            "passed": true,
            "score": 100,
            "weight": 0.1
          },
          {
            "name": "Claire Latour: private_secrets",
            "category": "validation",
            "passed": true,
            "score": 100,
            "weight": 0.1
          },
          {
            "name": "Claire Latour: stakes",
            "category": "validation",
            "passed": true,
            "score": 100,
            "weight": 0.1
          },
          {
            "name": "Alan Devereux: character_name",
            "category": "validation",
            "passed": true,
            "score": 100,
            "weight": 0.1
          },
          {
            "name": "Alan Devereux: public_persona",
            "category": "validation",
            "passed": true,
            "score": 100,
            "weight": 0.1
          },
          {
            "name": "Alan Devereux: private_secrets",
            "category": "validation",
            "passed": true,
            "score": 100,
            "weight": 0.1
          },
          {
            "name": "Alan Devereux: stakes",
            "category": "validation",
            "passed": true,
            "score": 100,
            "weight": 0.1
          },
          {
            "name": "Profile validity rate",
            "category": "validation",
            "passed": true,
            "score": 100,
            "weight": 2,
            "message": "100% valid"
          },
          {
            "name": "Profile narrative depth",
            "category": "quality",
            "passed": true,
            "score": 100,
            "weight": 2,
            "message": "Average depth: 81%"
          },
          {
            "name": "Humour style richness",
            "category": "quality",
            "passed": true,
            "score": 100,
            "weight": 1,
            "message": "5/5 profiles"
          },
          {
            "name": "Distinct personalities",
            "category": "quality",
            "passed": true,
            "score": 100,
            "weight": 1,
            "message": "100% distinct"
          },
          {
            "name": "Minimum profiles",
            "category": "completeness",
            "passed": true,
            "score": 100,
            "weight": 2,
            "message": "5 profiles"
          },
          {
            "name": "Field completeness",
            "category": "completeness",
            "passed": true,
            "score": 100,
            "weight": 1,
            "message": "100% fields filled"
          },
          {
            "name": "No duplicate names",
            "category": "consistency",
            "passed": true,
            "score": 100,
            "weight": 1
          },
          {
            "name": "Names match cast",
            "category": "consistency",
            "passed": true,
            "score": 100,
            "weight": 1,
            "message": "100% match"
          }
        ]
      },
      "duration_ms": 66171,
      "cost": 0.0070941684,
      "threshold": 75,
      "passed": true,
      "tests": [
        {
          "name": "Profiles array exists",
          "category": "validation",
          "passed": true,
          "score": 100,
          "weight": 1
        },
        {
          "name": "Antoinette Vaux: character_name",
          "category": "validation",
          "passed": true,
          "score": 100,
          "weight": 0.1
        },
        {
          "name": "Antoinette Vaux: public_persona",
          "category": "validation",
          "passed": true,
          "score": 100,
          "weight": 0.1
        },
        {
          "name": "Antoinette Vaux: private_secrets",
          "category": "validation",
          "passed": true,
          "score": 100,
          "weight": 0.1
        },
        {
          "name": "Antoinette Vaux: stakes",
          "category": "validation",
          "passed": true,
          "score": 100,
          "weight": 0.1
        },
        {
          "name": "Gordon Brabazon: character_name",
          "category": "validation",
          "passed": true,
          "score": 100,
          "weight": 0.1
        },
        {
          "name": "Gordon Brabazon: public_persona",
          "category": "validation",
          "passed": true,
          "score": 100,
          "weight": 0.1
        },
        {
          "name": "Gordon Brabazon: private_secrets",
          "category": "validation",
          "passed": true,
          "score": 100,
          "weight": 0.1
        },
        {
          "name": "Gordon Brabazon: stakes",
          "category": "validation",
          "passed": true,
          "score": 100,
          "weight": 0.1
        },
        {
          "name": "Paul Courtenay: character_name",
          "category": "validation",
          "passed": true,
          "score": 100,
          "weight": 0.1
        },
        {
          "name": "Paul Courtenay: public_persona",
          "category": "validation",
          "passed": true,
          "score": 100,
          "weight": 0.1
        },
        {
          "name": "Paul Courtenay: private_secrets",
          "category": "validation",
          "passed": true,
          "score": 100,
          "weight": 0.1
        },
        {
          "name": "Paul Courtenay: stakes",
          "category": "validation",
          "passed": true,
          "score": 100,
          "weight": 0.1
        },
        {
          "name": "Claire Latour: character_name",
          "category": "validation",
          "passed": true,
          "score": 100,
          "weight": 0.1
        },
        {
          "name": "Claire Latour: public_persona",
          "category": "validation",
          "passed": true,
          "score": 100,
          "weight": 0.1
        },
        {
          "name": "Claire Latour: private_secrets",
          "category": "validation",
          "passed": true,
          "score": 100,
          "weight": 0.1
        },
        {
          "name": "Claire Latour: stakes",
          "category": "validation",
          "passed": true,
          "score": 100,
          "weight": 0.1
        },
        {
          "name": "Alan Devereux: character_name",
          "category": "validation",
          "passed": true,
          "score": 100,
          "weight": 0.1
        },
        {
          "name": "Alan Devereux: public_persona",
          "category": "validation",
          "passed": true,
          "score": 100,
          "weight": 0.1
        },
        {
          "name": "Alan Devereux: private_secrets",
          "category": "validation",
          "passed": true,
          "score": 100,
          "weight": 0.1
        },
        {
          "name": "Alan Devereux: stakes",
          "category": "validation",
          "passed": true,
          "score": 100,
          "weight": 0.1
        },
        {
          "name": "Profile validity rate",
          "category": "validation",
          "passed": true,
          "score": 100,
          "weight": 2,
          "message": "100% valid"
        },
        {
          "name": "Profile narrative depth",
          "category": "quality",
          "passed": true,
          "score": 100,
          "weight": 2,
          "message": "Average depth: 81%"
        },
        {
          "name": "Humour style richness",
          "category": "quality",
          "passed": true,
          "score": 100,
          "weight": 1,
          "message": "5/5 profiles"
        },
        {
          "name": "Distinct personalities",
          "category": "quality",
          "passed": true,
          "score": 100,
          "weight": 1,
          "message": "100% distinct"
        },
        {
          "name": "Minimum profiles",
          "category": "completeness",
          "passed": true,
          "score": 100,
          "weight": 2,
          "message": "5 profiles"
        },
        {
          "name": "Field completeness",
          "category": "completeness",
          "passed": true,
          "score": 100,
          "weight": 1,
          "message": "100% fields filled"
        },
        {
          "name": "No duplicate names",
          "category": "consistency",
          "passed": true,
          "score": 100,
          "weight": 1
        },
        {
          "name": "Names match cast",
          "category": "consistency",
          "passed": true,
          "score": 100,
          "weight": 1,
          "message": "100% match"
        }
      ]
    },
    {
      "agent": "agent2c_location_profiles",
      "phase_name": "Location Profiles",
      "score": {
        "agent": "agent2c-location-profiles",
        "validation_score": 99.99999999999997,
        "quality_score": 100,
        "completeness_score": 100,
        "consistency_score": 100,
        "total": 100,
        "grade": "A",
        "passed": true,
        "tests": [
          {
            "name": "Profiles array exists",
            "category": "validation",
            "passed": true,
            "score": 100,
            "weight": 1
          },
          {
            "name": "The Library: Visual sense",
            "category": "validation",
            "passed": true,
            "score": 100,
            "weight": 0.1
          },
          {
            "name": "The Library: Auditory sense",
            "category": "validation",
            "passed": true,
            "score": 100,
            "weight": 0.1
          },
          {
            "name": "The Library: Olfactory sense",
            "category": "validation",
            "passed": true,
            "score": 100,
            "weight": 0.1
          },
          {
            "name": "The Library: Tactile sense",
            "category": "validation",
            "passed": true,
            "score": 100,
            "weight": 0.1
          },
          {
            "name": "The Library: Taste sense",
            "category": "validation",
            "passed": true,
            "score": 100,
            "weight": 0.1
          },
          {
            "name": "The Library: Geographic grounding",
            "category": "validation",
            "passed": true,
            "score": 100,
            "weight": 0.1
          },
          {
            "name": "The Library: Atmosphere",
            "category": "validation",
            "passed": true,
            "score": 100,
            "weight": 0.1
          },
          {
            "name": "The Drawing Room: Visual sense",
            "category": "validation",
            "passed": true,
            "score": 100,
            "weight": 0.1
          },
          {
            "name": "The Drawing Room: Auditory sense",
            "category": "validation",
            "passed": true,
            "score": 100,
            "weight": 0.1
          },
          {
            "name": "The Drawing Room: Olfactory sense",
            "category": "validation",
            "passed": true,
            "score": 100,
            "weight": 0.1
          },
          {
            "name": "The Drawing Room: Tactile sense",
            "category": "validation",
            "passed": true,
            "score": 100,
            "weight": 0.1
          },
          {
            "name": "The Drawing Room: Taste sense",
            "category": "validation",
            "passed": true,
            "score": 100,
            "weight": 0.1
          },
          {
            "name": "The Drawing Room: Geographic grounding",
            "category": "validation",
            "passed": true,
            "score": 100,
            "weight": 0.1
          },
          {
            "name": "The Drawing Room: Atmosphere",
            "category": "validation",
            "passed": true,
            "score": 100,
            "weight": 0.1
          },
          {
            "name": "The Master Bedroom: Visual sense",
            "category": "validation",
            "passed": true,
            "score": 100,
            "weight": 0.1
          },
          {
            "name": "The Master Bedroom: Auditory sense",
            "category": "validation",
            "passed": true,
            "score": 100,
            "weight": 0.1
          },
          {
            "name": "The Master Bedroom: Olfactory sense",
            "category": "validation",
            "passed": true,
            "score": 100,
            "weight": 0.1
          },
          {
            "name": "The Master Bedroom: Tactile sense",
            "category": "validation",
            "passed": true,
            "score": 100,
            "weight": 0.1
          },
          {
            "name": "The Master Bedroom: Taste sense",
            "category": "validation",
            "passed": true,
            "score": 100,
            "weight": 0.1
          },
          {
            "name": "The Master Bedroom: Geographic grounding",
            "category": "validation",
            "passed": true,
            "score": 100,
            "weight": 0.1
          },
          {
            "name": "The Master Bedroom: Atmosphere",
            "category": "validation",
            "passed": true,
            "score": 100,
            "weight": 0.1
          },
          {
            "name": "Profile validity rate",
            "category": "validation",
            "passed": true,
            "score": 100,
            "weight": 2,
            "message": "100% valid"
          },
          {
            "name": "Sensory richness",
            "category": "quality",
            "passed": true,
            "score": 100,
            "weight": 2,
            "message": "Average: 97%"
          },
          {
            "name": "Geographic specificity",
            "category": "quality",
            "passed": true,
            "score": 100,
            "weight": 1,
            "message": "3/3 specific"
          },
          {
            "name": "Minimum locations",
            "category": "completeness",
            "passed": true,
            "score": 100,
            "weight": 1.5,
            "message": "3 locations"
          },
          {
            "name": "All senses covered",
            "category": "completeness",
            "passed": true,
            "score": 100,
            "weight": 1.5,
            "message": "3/3 locations"
          },
          {
            "name": "No duplicate locations",
            "category": "consistency",
            "passed": true,
            "score": 100,
            "weight": 1
          }
        ]
      },
      "duration_ms": 72605,
      "cost": 0.007806140100000001,
      "threshold": 75,
      "passed": true,
      "tests": [
        {
          "name": "Profiles array exists",
          "category": "validation",
          "passed": true,
          "score": 100,
          "weight": 1
        },
        {
          "name": "The Library: Visual sense",
          "category": "validation",
          "passed": true,
          "score": 100,
          "weight": 0.1
        },
        {
          "name": "The Library: Auditory sense",
          "category": "validation",
          "passed": true,
          "score": 100,
          "weight": 0.1
        },
        {
          "name": "The Library: Olfactory sense",
          "category": "validation",
          "passed": true,
          "score": 100,
          "weight": 0.1
        },
        {
          "name": "The Library: Tactile sense",
          "category": "validation",
          "passed": true,
          "score": 100,
          "weight": 0.1
        },
        {
          "name": "The Library: Taste sense",
          "category": "validation",
          "passed": true,
          "score": 100,
          "weight": 0.1
        },
        {
          "name": "The Library: Geographic grounding",
          "category": "validation",
          "passed": true,
          "score": 100,
          "weight": 0.1
        },
        {
          "name": "The Library: Atmosphere",
          "category": "validation",
          "passed": true,
          "score": 100,
          "weight": 0.1
        },
        {
          "name": "The Drawing Room: Visual sense",
          "category": "validation",
          "passed": true,
          "score": 100,
          "weight": 0.1
        },
        {
          "name": "The Drawing Room: Auditory sense",
          "category": "validation",
          "passed": true,
          "score": 100,
          "weight": 0.1
        },
        {
          "name": "The Drawing Room: Olfactory sense",
          "category": "validation",
          "passed": true,
          "score": 100,
          "weight": 0.1
        },
        {
          "name": "The Drawing Room: Tactile sense",
          "category": "validation",
          "passed": true,
          "score": 100,
          "weight": 0.1
        },
        {
          "name": "The Drawing Room: Taste sense",
          "category": "validation",
          "passed": true,
          "score": 100,
          "weight": 0.1
        },
        {
          "name": "The Drawing Room: Geographic grounding",
          "category": "validation",
          "passed": true,
          "score": 100,
          "weight": 0.1
        },
        {
          "name": "The Drawing Room: Atmosphere",
          "category": "validation",
          "passed": true,
          "score": 100,
          "weight": 0.1
        },
        {
          "name": "The Master Bedroom: Visual sense",
          "category": "validation",
          "passed": true,
          "score": 100,
          "weight": 0.1
        },
        {
          "name": "The Master Bedroom: Auditory sense",
          "category": "validation",
          "passed": true,
          "score": 100,
          "weight": 0.1
        },
        {
          "name": "The Master Bedroom: Olfactory sense",
          "category": "validation",
          "passed": true,
          "score": 100,
          "weight": 0.1
        },
        {
          "name": "The Master Bedroom: Tactile sense",
          "category": "validation",
          "passed": true,
          "score": 100,
          "weight": 0.1
        },
        {
          "name": "The Master Bedroom: Taste sense",
          "category": "validation",
          "passed": true,
          "score": 100,
          "weight": 0.1
        },
        {
          "name": "The Master Bedroom: Geographic grounding",
          "category": "validation",
          "passed": true,
          "score": 100,
          "weight": 0.1
        },
        {
          "name": "The Master Bedroom: Atmosphere",
          "category": "validation",
          "passed": true,
          "score": 100,
          "weight": 0.1
        },
        {
          "name": "Profile validity rate",
          "category": "validation",
          "passed": true,
          "score": 100,
          "weight": 2,
          "message": "100% valid"
        },
        {
          "name": "Sensory richness",
          "category": "quality",
          "passed": true,
          "score": 100,
          "weight": 2,
          "message": "Average: 97%"
        },
        {
          "name": "Geographic specificity",
          "category": "quality",
          "passed": true,
          "score": 100,
          "weight": 1,
          "message": "3/3 specific"
        },
        {
          "name": "Minimum locations",
          "category": "completeness",
          "passed": true,
          "score": 100,
          "weight": 1.5,
          "message": "3 locations"
        },
        {
          "name": "All senses covered",
          "category": "completeness",
          "passed": true,
          "score": 100,
          "weight": 1.5,
          "message": "3/3 locations"
        },
        {
          "name": "No duplicate locations",
          "category": "consistency",
          "passed": true,
          "score": 100,
          "weight": 1
        }
      ]
    },
    {
      "agent": "agent2d_temporal_context",
      "phase_name": "Temporal Context",
      "score": {
        "agent": "agent2d-temporal-context",
        "validation_score": 100,
        "quality_score": 83.33333333333333,
        "completeness_score": 75,
        "consistency_score": 100,
        "total": 90,
        "grade": "A",
        "passed": true,
        "tests": [
          {
            "name": "specific_date present",
            "category": "validation",
            "passed": true,
            "score": 100,
            "weight": 0.5
          },
          {
            "name": "time_of_day present",
            "category": "validation",
            "passed": true,
            "score": 100,
            "weight": 0.5
          },
          {
            "name": "season present",
            "category": "validation",
            "passed": true,
            "score": 100,
            "weight": 0.5
          },
          {
            "name": "weather_patterns present",
            "category": "validation",
            "passed": true,
            "score": 100,
            "weight": 0.5
          },
          {
            "name": "Date specificity",
            "category": "validation",
            "passed": true,
            "score": 100,
            "weight": 1,
            "message": "Full date specified"
          },
          {
            "name": "Time specificity",
            "category": "validation",
            "passed": true,
            "score": 100,
            "weight": 1,
            "message": "Specific time given"
          },
          {
            "name": "Weather detail",
            "category": "quality",
            "passed": true,
            "score": 100,
            "weight": 1,
            "message": "90% richness"
          },
          {
            "name": "Fashion detail",
            "category": "quality",
            "passed": false,
            "score": 50,
            "weight": 1,
            "message": "50% richness"
          },
          {
            "name": "Temporal richness",
            "category": "quality",
            "passed": true,
            "score": 100,
            "weight": 1,
            "message": "244 words"
          },
          {
            "name": "Optional fields",
            "category": "completeness",
            "passed": true,
            "score": 100,
            "weight": 1.5,
            "message": "All optional fields present"
          },
          {
            "name": "Substantial content",
            "category": "completeness",
            "passed": false,
            "score": 50,
            "weight": 1.5,
            "message": "2/4 fields detailed"
          },
          {
            "name": "Season/weather consistency",
            "category": "consistency",
            "passed": true,
            "score": 100,
            "weight": 1
          }
        ]
      },
      "duration_ms": 12328,
      "cost": 0.00101712105,
      "threshold": 70,
      "passed": true,
      "tests": [
        {
          "name": "specific_date present",
          "category": "validation",
          "passed": true,
          "score": 100,
          "weight": 0.5
        },
        {
          "name": "time_of_day present",
          "category": "validation",
          "passed": true,
          "score": 100,
          "weight": 0.5
        },
        {
          "name": "season present",
          "category": "validation",
          "passed": true,
          "score": 100,
          "weight": 0.5
        },
        {
          "name": "weather_patterns present",
          "category": "validation",
          "passed": true,
          "score": 100,
          "weight": 0.5
        },
        {
          "name": "Date specificity",
          "category": "validation",
          "passed": true,
          "score": 100,
          "weight": 1,
          "message": "Full date specified"
        },
        {
          "name": "Time specificity",
          "category": "validation",
          "passed": true,
          "score": 100,
          "weight": 1,
          "message": "Specific time given"
        },
        {
          "name": "Weather detail",
          "category": "quality",
          "passed": true,
          "score": 100,
          "weight": 1,
          "message": "90% richness"
        },
        {
          "name": "Fashion detail",
          "category": "quality",
          "passed": false,
          "score": 50,
          "weight": 1,
          "message": "50% richness"
        },
        {
          "name": "Temporal richness",
          "category": "quality",
          "passed": true,
          "score": 100,
          "weight": 1,
          "message": "244 words"
        },
        {
          "name": "Optional fields",
          "category": "completeness",
          "passed": true,
          "score": 100,
          "weight": 1.5,
          "message": "All optional fields present"
        },
        {
          "name": "Substantial content",
          "category": "completeness",
          "passed": false,
          "score": 50,
          "weight": 1.5,
          "message": "2/4 fields detailed"
        },
        {
          "name": "Season/weather consistency",
          "category": "consistency",
          "passed": true,
          "score": 100,
          "weight": 1
        }
      ]
    }
  ],
  "summary": {
    "phases_passed": 12,
    "phases_failed": 0,
    "total_phases": 12,
    "pass_rate": 100,
    "weakest_phase": "Temporal Context",
    "strongest_phase": "Location Profiles",
    "retry_stats": {
      "total_retries": 0,
      "phases_retried": 0,
      "retry_rate": "0.00",
      "retried_phases": []
    },
    "total_cost": 0.024
  },
  "threshold_config": {
    "mode": "standard"
  },
  "aborted": true,
  "abort_reason": "Chapter 1 generation failed after 3 attempts: (scene.setting || scene.location || \"\").toLowerCase is not a function"
}